hotel_coupon_app_package_alexandermamani/__init__.py
hotel_coupon_app_package_alexandermamani/aws_services.py
hotel_coupon_app_package_alexandermamani/report_pdf.py
hotel_coupon_app_package_alexandermamani-1.1.8.dist-info/METADATA
hotel_coupon_app_package_alexandermamani-1.1.8.dist-info/WHEEL
hotel_coupon_app_package_alexandermamani-1.1.8.dist-info/licenses/LICENSE
hotel_coupon_app_package_alexandermamani-1.1.8.dist-info/RECORD
