Metadata-Version: 2.4
Name: hotel_coupon_app_package_alexandermamani
Version: 1.1.8
Summary: Custom libraries for hotelier coupon app.
Project-URL: Homepage, https://github.com/alexandermamaniyucra/hotelier_coupon_resources_library
Project-URL: Issues, https://github.com/alexandermamaniyucra/hotelier_coupon_resources_library/issues
Author-email: Alexander Mamani <x233298@student.ncirl.ie>
License-File: LICENSE
Keywords: SNS,SQS,hotel_coupon_app_package_alexandermamani,hotelier_coupon_resources,report_PDF
Classifier: License :: OSI Approved :: MIT License
Classifier: Operating System :: OS Independent
Classifier: Programming Language :: Python :: 3
Requires-Python: >=3.9
